mkdocs_translations/__init__.py
mkdocs_translations/plugin.py
mkdocs_translations-0.1.1.dist-info/entry_points.txt
mkdocs_translations-0.1.1.dist-info/WHEEL
mkdocs_translations-0.1.1.dist-info/METADATA
mkdocs_translations-0.1.1.dist-info/RECORD
