Metadata-Version: 2.1
Name: mkdocs-translations
Version: 0.1.1
Summary: Internationalization plugin for mkdocs
Keywords: mkdocs,plugin,i18n,translate,translations
Author: Pavel Kirilin
Author-email: win10@list.ru
Maintainer: Pavel Kirilin
Maintainer-email: win10@list.ru
Requires-Python: >=3.8,<4.0
Classifier: Programming Language :: Python
Classifier: Programming Language :: Python :: 3
Classifier: Programming Language :: Python :: 3 :: Only
Classifier: Programming Language :: Python :: 3.8
Classifier: Programming Language :: Python :: 3.9
Requires-Dist: loguru (>=0.5.3,<0.6.0)
Requires-Dist: mkdocs (>=1.1.2,<2.0.0)
